[
  {
    "title": "SSD NVMe 1TB",
    "category": "Almacenamiento",
    "store": "Thot Computacion",
    "priceText": "US$ 89",
    "oldPriceText": "US$ 109",
    "badge": "Oferta del dia",
    "text": "Buen punto de entrada para actualizar una PC gamer o notebook compatible.",
    "url": "https://thotcomputacion.com.uy/",
    "image": "assets/deals/ssd-nvme.svg",
    "tone": "green"
  },
  {
    "title": "Monitor 24 pulgadas 100Hz",
    "category": "Monitores",
    "store": "Hard PC",
    "priceText": "US$ 119",
    "oldPriceText": "US$ 139",
    "badge": "Popular",
    "text": "Formato comodo para escritorio, estudio y gaming casual.",
    "url": "https://www.hardpc.com.uy/",
    "image": "assets/deals/monitor-24.svg",
    "tone": "graphite"
  },
  {
    "title": "Mouse gamer inalambrico",
    "category": "Perifericos",
    "store": "Banifox",
    "priceText": "US$ 24",
    "oldPriceText": "US$ 32",
    "badge": "Precio bajo",
    "text": "Accesorio rapido para completar setup sin gastar demasiado.",
    "url": "https://www.banifox.com/",
    "image": "assets/deals/mouse-gamer.svg",
    "tone": "amber"
  }
]
